[
    {
        "name": "Apple",
        "symbol": "AAPL",
        "lastsale": 138.85,
        "netchange": -1.57,
        "pctchange": -1.118,
        "volume": 15861820,
        "marketCap": 2407289659000.0,
        "country": "United States",
        "ipoyear": "1980",
        "industry": "Computer Manufacturing",
        "sector": "Technology",
        "url": "/market-activity/stocks/aapl",
        "assettype": "Stock",
        "rank": 1,
        "tarih": "11.10.2022 14:41:07"
    },
    {
        "name": "Microsoft",
        "symbol": "MSFT",
        "lastsale": 225.76,
        "netchange": -3.49,
        "pctchange": -1.522,
        "volume": 5993439,
        "marketCap": 1683693669023.0,
        "country": "United States",
        "ipoyear": "1986",
        "industry": "Computer Software: Prepackaged Software",
        "sector": "Technology",
        "url": "/market-activity/stocks/msft",
        "assettype": "Stock",
        "rank": 2,
        "tarih": "11.10.2022 14:41:07"
    },
    {
        "name": "Alphabet",
        "symbol": "GOOGL",
        "lastsale": 96.93,
        "netchange": -0.93,
        "pctchange": -0.95,
        "volume": 4752508,
        "marketCap": 1264354920000.0,
        "country": "United States",
        "ipoyear": "2004",
        "industry": "Internet and Information Services",
        "sector": "Technology",
        "url": "/market-activity/stocks/googl",
        "assettype": "Stock",
        "rank": 3,
        "tarih": "11.10.2022 14:41:07"
    },
    {
        "name": "Bitcoin",
        "symbol": "btc",
        "lastsale": 19023.66,
        "netchange": -286.99266530366367,
        "pctchange": -1.48619,
        "volume": 25124056749,
        "marketCap": 364802668634.0,
        "country": "",
        "ipoyear": "",
        "industry": "Crypto",
        "sector": "Technology",
        "url": "",
        "assettype": "Crypto",
        "rank": 4,
        "tarih": "11.10.2022 14:41:07"
    },
    {
        "name": "Meta Platforms",
        "symbol": "META",
        "lastsale": 127.31,
        "netchange": -6.48,
        "pctchange": -4.843,
        "volume": 9642808,
        "marketCap": 342151795970.0,
        "country": "United States",
        "ipoyear": "2012",
        "industry": "Internet and Information Services",
        "sector": "Technology",
        "url": "/market-activity/stocks/meta",
        "assettype": "Stock",
        "rank": 5,
        "tarih": "11.10.2022 14:41:07"
    },
    {
        "name": "NVIDIA",
        "symbol": "NVDA",
        "lastsale": 113.54,
        "netchange": -3.16,
        "pctchange": -2.708,
        "volume": 13180038,
        "marketCap": 282714600000.0,
        "country": "United States",
        "ipoyear": "1999",
        "industry": "Semiconductors",
        "sector": "Technology",
        "url": "/market-activity/stocks/nvda",
        "assettype": "Stock",
        "rank": 6,
        "tarih": "11.10.2022 14:41:07"
    },
    {
        "name": "Broadcom",
        "symbol": "AVGO",
        "lastsale": 429.855,
        "netchange": -7.845,
        "pctchange": -1.792,
        "volume": 465610,
        "marketCap": 174094620991.0,
        "country": "United States",
        "ipoyear": "2009",
        "industry": "Semiconductors",
        "sector": "Technology",
        "url": "/market-activity/stocks/avgo",
        "assettype": "Stock",
        "rank": 7,
        "tarih": "11.10.2022 14:41:07"
    },
    {
        "name": "Oracle",
        "symbol": "ORCL",
        "lastsale": 61.855,
        "netchange": -0.715,
        "pctchange": -1.143,
        "volume": 659031,
        "marketCap": 166771367414.0,
        "country": "United States",
        "ipoyear": "1986",
        "industry": "Computer Software: Prepackaged Software",
        "sector": "Technology",
        "url": "/market-activity/stocks/orcl",
        "assettype": "Stock",
        "rank": 8,
        "tarih": "11.10.2022 14:41:07"
    },
    {
        "name": "Salesforce",
        "symbol": "CRM",
        "lastsale": 140.39,
        "netchange": -5.25,
        "pctchange": -3.605,
        "volume": 1368666,
        "marketCap": 140390000000.0,
        "country": "United States",
        "ipoyear": "2004",
        "industry": "Computer Software: Prepackaged Software",
        "sector": "Technology",
        "url": "/market-activity/stocks/crm",
        "assettype": "Stock",
        "rank": 9,
        "tarih": "11.10.2022 14:41:07"
    },
    {
        "name": "Texas Instruments",
        "symbol": "TXN",
        "lastsale": 152.85,
        "netchange": -3.94,
        "pctchange": -2.513,
        "volume": 1671386,
        "marketCap": 139660170740.0,
        "country": "United States",
        "ipoyear": "",
        "industry": "Semiconductors",
        "sector": "Technology",
        "url": "/market-activity/stocks/txn",
        "assettype": "Stock",
        "rank": 10,
        "tarih": "11.10.2022 14:41:07"
    }
]