[
  {
    "number": 6038,
    "shortRate": 86.79,
    "longRate": 13.21,
    "longVolUsd": 9768823.76271,
    "rate": 45.66,
    "shortVolUsd": 64155094.99011,
    "exchangeName": "OKX",
    "totalVolUsd": 73923918.75282,
    "averagePrice": 12243.1134,
    "exchangeLogo": "https://cdn.coinglasscdn.com/static/exchanges/OKX.png",
    "rank": 1,
    "datetime": "2023-01-12 00:04:28"
  },
  {
    "number": 14831,
    "shortRate": 73.55,
    "longRate": 26.45,
    "longVolUsd": 9077113.31097167,
    "rate": 21.2,
    "shortVolUsd": 25246511.99614635,
    "exchangeName": "Binance",
    "totalVolUsd": 34323625.30711802,
    "averagePrice": 2314.3163,
    "exchangeLogo": "https://cdn.coinglasscdn.com/static/exchanges/270.png",
    "rank": 2,
    "datetime": "2023-01-12 00:04:28"
  },
  {
    "number": 1846,
    "shortRate": 92.09,
    "longRate": 7.91,
    "longVolUsd": 1493781.50172,
    "rate": 11.67,
    "shortVolUsd": 17397421.20404,
    "exchangeName": "Huobi",
    "totalVolUsd": 18891202.70576,
    "averagePrice": 10233.5876,
    "exchangeLogo": "https://cdn.coinglasscdn.com/static/exchanges/2502.png",
    "rank": 3,
    "datetime": "2023-01-12 00:04:28"
  },
  {
    "number": 5378,
    "shortRate": 69.88,
    "longRate": 30.12,
    "longVolUsd": 5501353.740336,
    "rate": 11.28,
    "shortVolUsd": 12765412.076628,
    "exchangeName": "Bybit",
    "totalVolUsd": 18266765.816964,
    "averagePrice": 3396.5723,
    "exchangeLogo": "https://cdn.coinglasscdn.com/static/exchanges/521.png",
    "rank": 4,
    "datetime": "2023-01-12 00:04:28"
  },
  {
    "number": 3045,
    "shortRate": 87.03,
    "longRate": 12.97,
    "longVolUsd": 832974.12104404,
    "rate": 3.97,
    "shortVolUsd": 5587572.03976398,
    "exchangeName": "CoinEx",
    "totalVolUsd": 6420546.16080802,
    "averagePrice": 2108.5537,
    "exchangeLogo": "https://cdn.sampyun.com/static/exchanges/CoinEx.png",
    "rank": 5,
    "datetime": "2023-01-12 00:04:28"
  },
  {
    "number": 885,
    "shortRate": 95.64,
    "longRate": 4.36,
    "longVolUsd": 225080.101,
    "rate": 3.19,
    "shortVolUsd": 4936383.558,
    "exchangeName": "Deribit",
    "totalVolUsd": 5161463.659,
    "averagePrice": 5832.1623,
    "exchangeLogo": "https://cdn.coinglasscdn.com/static/exchanges/deribit.png",
    "rank": 6,
    "datetime": "2023-01-12 00:04:28"
  },
  {
    "number": 88,
    "shortRate": 85.64,
    "longRate": 14.36,
    "longVolUsd": 368044.11232375,
    "rate": 1.58,
    "shortVolUsd": 2195823.26251516,
    "exchangeName": "Bitmex",
    "totalVolUsd": 2563867.37483891,
    "averagePrice": 29134.8565,
    "exchangeLogo": "https://cdn.coinglasscdn.com/static/exchanges/157.png",
    "rank": 7,
    "datetime": "2023-01-12 00:04:28"
  },
  {
    "number": 804,
    "shortRate": 4.38,
    "longRate": 95.62,
    "longVolUsd": 2239962.60843705,
    "rate": 1.45,
    "shortVolUsd": 102521.76885689,
    "exchangeName": "Bitfinex",
    "totalVolUsd": 2342484.37729394,
    "averagePrice": 2913.5378,
    "exchangeLogo": "https://cdn.coinglasscdn.com/static/exchanges/bitfinex.jpg",
    "rank": 8,
    "datetime": "2023-01-12 00:04:28"
  }
]