[
  {
    "number": 1626,
    "shortRate": 24.16,
    "longRate": 75.84,
    "longVolUsd": 5195177.01543,
    "rate": 33.58,
    "shortVolUsd": 1654553.33667,
    "exchangeName": "OKX",
    "totalVolUsd": 6849730.3521,
    "averagePrice": 4212.6263,
    "exchangeLogo": "https://cdn.coinglasscdn.com/static/exchanges/OKX.png",
    "rank": 1,
    "datetime": "2023-01-06 06:01:47"
  },
  {
    "number": 4150,
    "shortRate": 29.31,
    "longRate": 70.69,
    "longVolUsd": 4168509.34564958,
    "rate": 28.91,
    "shortVolUsd": 1728504.6575802,
    "exchangeName": "Binance",
    "totalVolUsd": 5897014.00322978,
    "averagePrice": 1420.9672,
    "exchangeLogo": "https://cdn.coinglasscdn.com/static/exchanges/270.png",
    "rank": 2,
    "datetime": "2023-01-06 06:01:47"
  },
  {
    "number": 2178,
    "shortRate": 39.75,
    "longRate": 60.25,
    "longVolUsd": 2693318.925633,
    "rate": 21.91,
    "shortVolUsd": 1776616.24689,
    "exchangeName": "Bybit",
    "totalVolUsd": 4469935.172523,
    "averagePrice": 2052.3118,
    "exchangeLogo": "https://cdn.coinglasscdn.com/static/exchanges/521.png",
    "rank": 3,
    "datetime": "2023-01-06 06:01:47"
  },
  {
    "number": 643,
    "shortRate": 17.39,
    "longRate": 82.61,
    "longVolUsd": 1289697.21665,
    "rate": 7.65,
    "shortVolUsd": 271451.71149,
    "exchangeName": "Huobi",
    "totalVolUsd": 1561148.92814,
    "averagePrice": 2427.9144,
    "exchangeLogo": "https://cdn.coinglasscdn.com/static/exchanges/2502.png",
    "rank": 4,
    "datetime": "2023-01-06 06:01:47"
  },
  {
    "number": 1345,
    "shortRate": 29.96,
    "longRate": 70.04,
    "longVolUsd": 862258.77692707,
    "rate": 6.03,
    "shortVolUsd": 368861.98607884,
    "exchangeName": "CoinEx",
    "totalVolUsd": 1231120.76300591,
    "averagePrice": 915.3314,
    "exchangeLogo": "https://cdn.sampyun.com/static/exchanges/CoinEx.png",
    "rank": 5,
    "datetime": "2023-01-06 06:01:47"
  },
  {
    "number": 39,
    "shortRate": 100.0,
    "longRate": 0.0,
    "longVolUsd": 0,
    "rate": 1.66,
    "shortVolUsd": 339001.0,
    "exchangeName": "Deribit",
    "totalVolUsd": 339001.0,
    "averagePrice": 8692.3333,
    "exchangeLogo": "https://cdn.coinglasscdn.com/static/exchanges/deribit.png",
    "rank": 6,
    "datetime": "2023-01-06 06:01:47"
  },
  {
    "number": 8,
    "shortRate": 38.58,
    "longRate": 61.42,
    "longVolUsd": 22531.78691081,
    "rate": 0.18,
    "shortVolUsd": 14155.753786,
    "exchangeName": "Bitmex",
    "totalVolUsd": 36687.54069681,
    "averagePrice": 4585.9426,
    "exchangeLogo": "https://cdn.coinglasscdn.com/static/exchanges/157.png",
    "rank": 7,
    "datetime": "2023-01-06 06:01:47"
  },
  {
    "number": 40,
    "shortRate": 100.0,
    "longRate": 0.0,
    "longVolUsd": 0.0087364,
    "rate": 0.08,
    "shortVolUsd": 16405.69824796,
    "exchangeName": "Bitfinex",
    "totalVolUsd": 16405.70698436,
    "averagePrice": 410.1427,
    "exchangeLogo": "https://cdn.coinglasscdn.com/static/exchanges/bitfinex.jpg",
    "rank": 8,
    "datetime": "2023-01-06 06:01:47"
  }
]