[
  {
    "number": 8596,
    "shortRate": 91.52,
    "longRate": 8.48,
    "longVolUsd": 1343869.5960494,
    "rate": 41.32,
    "shortVolUsd": 14509221.21532667,
    "exchangeName": "Binance",
    "totalVolUsd": 15853090.81137607,
    "averagePrice": 1844.2404,
    "exchangeLogo": "https://cdn.coinglasscdn.com/static/exchanges/270.png",
    "rank": 1,
    "datetime": "2023-01-07 16:01:52"
  },
  {
    "number": 2261,
    "shortRate": 89.19,
    "longRate": 10.81,
    "longVolUsd": 1207777.58982,
    "rate": 29.13,
    "shortVolUsd": 9969302.30119,
    "exchangeName": "OKX",
    "totalVolUsd": 11177079.89101,
    "averagePrice": 4943.4232,
    "exchangeLogo": "https://cdn.coinglasscdn.com/static/exchanges/OKX.png",
    "rank": 2,
    "datetime": "2023-01-07 16:01:52"
  },
  {
    "number": 2716,
    "shortRate": 76.45,
    "longRate": 23.55,
    "longVolUsd": 1616370.839401,
    "rate": 17.89,
    "shortVolUsd": 5247720.676497,
    "exchangeName": "Bybit",
    "totalVolUsd": 6864091.515898,
    "averagePrice": 2527.2796,
    "exchangeLogo": "https://cdn.coinglasscdn.com/static/exchanges/521.png",
    "rank": 3,
    "datetime": "2023-01-07 16:01:52"
  },
  {
    "number": 498,
    "shortRate": 87.83,
    "longRate": 12.17,
    "longVolUsd": 331587.47569,
    "rate": 7.1,
    "shortVolUsd": 2392024.98172,
    "exchangeName": "Huobi",
    "totalVolUsd": 2723612.45741,
    "averagePrice": 5469.1013,
    "exchangeLogo": "https://cdn.coinglasscdn.com/static/exchanges/2502.png",
    "rank": 4,
    "datetime": "2023-01-07 16:01:52"
  },
  {
    "number": 1838,
    "shortRate": 82.7,
    "longRate": 17.3,
    "longVolUsd": 287621.04612572,
    "rate": 4.33,
    "shortVolUsd": 1374626.81974267,
    "exchangeName": "CoinEx",
    "totalVolUsd": 1662247.86586839,
    "averagePrice": 904.3786,
    "exchangeLogo": "https://cdn.sampyun.com/static/exchanges/CoinEx.png",
    "rank": 5,
    "datetime": "2023-01-07 16:01:52"
  },
  {
    "number": 11,
    "shortRate": 100.0,
    "longRate": 0.0,
    "longVolUsd": 0.6577806,
    "rate": 0.18,
    "shortVolUsd": 69508.6266458,
    "exchangeName": "Bitmex",
    "totalVolUsd": 69509.2844264,
    "averagePrice": 6319.0259,
    "exchangeLogo": "https://cdn.coinglasscdn.com/static/exchanges/157.png",
    "rank": 6,
    "datetime": "2023-01-07 16:01:52"
  },
  {
    "number": 36,
    "shortRate": 14.14,
    "longRate": 85.86,
    "longVolUsd": 17224.24688229,
    "rate": 0.05,
    "shortVolUsd": 2836.7365577,
    "exchangeName": "Bitfinex",
    "totalVolUsd": 20060.98343999,
    "averagePrice": 557.2495,
    "exchangeLogo": "https://cdn.coinglasscdn.com/static/exchanges/bitfinex.jpg",
    "rank": 7,
    "datetime": "2023-01-07 16:01:52"
  },
  {
    "number": 2,
    "shortRate": 100.0,
    "longRate": 0.0,
    "longVolUsd": 0,
    "rate": 0.0,
    "shortVolUsd": 1389.0,
    "exchangeName": "Deribit",
    "totalVolUsd": 1389.0,
    "averagePrice": 694.5,
    "exchangeLogo": "https://cdn.coinglasscdn.com/static/exchanges/deribit.png",
    "rank": 8,
    "datetime": "2023-01-07 16:01:52"
  }
]