[
  {
    "number": 16752,
    "shortRate": 43.41,
    "longRate": 56.59,
    "longVolUsd": 16480300.68474196,
    "rate": 37.86,
    "shortVolUsd": 12642231.32033375,
    "exchangeName": "Binance",
    "totalVolUsd": 29122532.00507571,
    "averagePrice": 1738.4511,
    "exchangeLogo": "https://cdn.coinglasscdn.com/static/exchanges/270.png",
    "rank": 1,
    "datetime": "2022-10-22 08:01:49"
  },
  {
    "number": 1670,
    "shortRate": 16.14,
    "longRate": 83.86,
    "longVolUsd": 11597026.60222,
    "rate": 17.98,
    "shortVolUsd": 2232337.1665,
    "exchangeName": "Okex",
    "totalVolUsd": 13829363.76872,
    "averagePrice": 8281.0561,
    "exchangeLogo": "https://cdn.coinglasscdn.com/static/exchanges/OKX.png",
    "rank": 2,
    "datetime": "2022-10-22 08:01:49"
  },
  {
    "number": 9083,
    "shortRate": 32.47,
    "longRate": 67.53,
    "longVolUsd": 8460560.6309957,
    "rate": 16.29,
    "shortVolUsd": 4068669.8553875,
    "exchangeName": "FTX",
    "totalVolUsd": 12529230.4863832,
    "averagePrice": 1379.4154,
    "exchangeLogo": "https://cdn.coinglasscdn.com/static/exchanges/524.png",
    "rank": 3,
    "datetime": "2022-10-22 08:01:49"
  },
  {
    "number": 3778,
    "shortRate": 53.44,
    "longRate": 46.56,
    "longVolUsd": 5302089.62695,
    "rate": 14.8,
    "shortVolUsd": 6084675.90077,
    "exchangeName": "Bybit",
    "totalVolUsd": 11386765.52772,
    "averagePrice": 3013.9665,
    "exchangeLogo": "https://cdn.coinglasscdn.com/static/exchanges/521.png",
    "rank": 4,
    "datetime": "2022-10-22 08:01:49"
  },
  {
    "number": 1474,
    "shortRate": 20.25,
    "longRate": 79.75,
    "longVolUsd": 4308384.16606,
    "rate": 7.02,
    "shortVolUsd": 1094050.9921,
    "exchangeName": "Huobi",
    "totalVolUsd": 5402435.15816,
    "averagePrice": 3665.1528,
    "exchangeLogo": "https://cdn.coinglasscdn.com/static/exchanges/2502.png",
    "rank": 5,
    "datetime": "2022-10-22 08:01:49"
  },
  {
    "number": 1626,
    "shortRate": 24.92,
    "longRate": 75.08,
    "longVolUsd": 2335948.29996691,
    "rate": 4.04,
    "shortVolUsd": 775394.53264643,
    "exchangeName": "CoinEx",
    "totalVolUsd": 3111342.83261334,
    "averagePrice": 1913.495,
    "exchangeLogo": "https://cdn.sampyun.com/static/exchanges/CoinEx.png",
    "rank": 6,
    "datetime": "2022-10-22 08:01:49"
  },
  {
    "number": 40,
    "shortRate": 20.32,
    "longRate": 79.68,
    "longVolUsd": 759787.30370697,
    "rate": 1.24,
    "shortVolUsd": 193753.8447623,
    "exchangeName": "Bitmex",
    "totalVolUsd": 953541.14846927,
    "averagePrice": 23838.5287,
    "exchangeLogo": "https://cdn.coinglasscdn.com/static/exchanges/157.png",
    "rank": 7,
    "datetime": "2022-10-22 08:01:49"
  },
  {
    "number": 180,
    "shortRate": 16.17,
    "longRate": 83.83,
    "longVolUsd": 494120.381,
    "rate": 0.77,
    "shortVolUsd": 95330.179,
    "exchangeName": "Deribit",
    "totalVolUsd": 589450.56,
    "averagePrice": 3274.7253,
    "exchangeLogo": "https://cdn.coinglasscdn.com/static/exchanges/deribit.png",
    "rank": 8,
    "datetime": "2022-10-22 08:01:49"
  },
  {
    "number": 0,
    "shortRate": 0,
    "amount": 0,
    "longRate": 0,
    "rate": 0,
    "exchangeName": "Bitfinex",
    "totalVolUsd": 0,
    "averagePrice": 0,
    "exchangeLogo": "https://cdn.coinglasscdn.com/static/exchanges/bitfinex.jpg",
    "rank": 9,
    "datetime": "2022-10-22 08:01:49"
  }
]