[
  {
    "name": "DeFi Pulse Index",
    "symbol": "dpi",
    "original_mcap": 20044186,
    "marketcap": "20.04M",
    "price_change": "0.15287%",
    "volume": "$100.88K",
    "circulating_supply": "302.11K",
    "date": "24.11.2022",
    "assets": [
      "UNI",
      "AAVE",
      "MKR",
      "LRC",
      "SNX",
      "COMP",
      "YFI",
      "SUSHI",
      "KNC",
      "REN",
      "BAL",
      "BADGER",
      "FARM",
      "RGT"
    ],
    "rank": 1
  },
  {
    "name": "Interest Compounding ETH Index",
    "symbol": "iceth",
    "original_mcap": 12150368,
    "marketcap": "12.15M",
    "price_change": "1.06846%",
    "volume": "$726.25K",
    "circulating_supply": "10.38K",
    "date": "24.11.2022",
    "assets": [
      "stETH",
      "WETH"
    ],
    "rank": 2
  },
  {
    "name": "Metaverse Index",
    "symbol": "mvi",
    "original_mcap": 3188548,
    "marketcap": "3.19M",
    "price_change": "2.8556%",
    "volume": "$13.8K",
    "circulating_supply": "166.89K",
    "date": "24.11.2022",
    "assets": [
      "ILV",
      "AXS",
      "SAND",
      "MANA",
      "ENJ",
      "WAXE",
      "RLY",
      "AUDIO",
      "YGG",
      "DG",
      "ERN",
      "NFTX",
      "Whale",
      "TVK",
      "RARI",
      "REVV"
    ],
    "rank": 3
  },
  {
    "name": "Bankless BED Index",
    "symbol": "bed",
    "original_mcap": 879519,
    "marketcap": "879.52K",
    "price_change": "0.0172%",
    "volume": "$1.97K",
    "circulating_supply": "20.67K",
    "date": "24.11.2022",
    "assets": [
      "WETH",
      "WBTC",
      "DPI"
    ],
    "rank": 4
  },
  {
    "name": "Data Economy Index",
    "symbol": "data",
    "original_mcap": 373507,
    "marketcap": "373.51K",
    "price_change": "2.16088%",
    "volume": "$757.83",
    "circulating_supply": "22.66K",
    "date": "24.11.2022",
    "assets": [
      "LINK",
      "FIL",
      "GRAPH",
      "BAT",
      "LPT",
      "ENS",
      "OCEAN",
      "NMR"
    ],
    "rank": 5
  },
  {
    "name": "Bankless DeFi Innovation Index",
    "symbol": "gmi",
    "original_mcap": 360647,
    "marketcap": "360.65K",
    "price_change": "-1.33276%",
    "volume": "$485.54",
    "circulating_supply": "26.63K",
    "date": "24.11.2022",
    "assets": [
      "CVX",
      "MPL",
      "TRIBE",
      "TOKE",
      "OLYMPUS",
      "RBN",
      "DYDX",
      "PERP",
      "FLX",
      "FXS",
      "ALCX",
      "DPX"
    ],
    "rank": 6
  },
  {
    "name": "JPG NFT Index",
    "symbol": "jpg",
    "original_mcap": 107819,
    "marketcap": "107.82K",
    "price_change": "1.53832%",
    "volume": "$169.48",
    "circulating_supply": "4.6K",
    "date": "24.11.2022",
    "assets": [
      "PUNK",
      "XMON",
      "WHALE",
      "SOCKS",
      "DOG",
      "ETH",
      "K21",
      "ASH",
      "uJenny"
    ],
    "rank": 7
  }
]