[
  {
    "name": "DeFi Pulse Index",
    "symbol": "dpi",
    "original_mcap": 20018857,
    "marketcap": "20.02M",
    "price_change": "1.70885%",
    "volume": "$112.64K",
    "circulating_supply": "302.11K",
    "date": "26.11.2022",
    "assets": [
      "UNI",
      "AAVE",
      "MKR",
      "LRC",
      "SNX",
      "COMP",
      "YFI",
      "SUSHI",
      "KNC",
      "REN",
      "BAL",
      "BADGER",
      "FARM",
      "RGT"
    ],
    "rank": 1
  },
  {
    "name": "Interest Compounding ETH Index",
    "symbol": "iceth",
    "original_mcap": 12416938,
    "marketcap": "12.42M",
    "price_change": "4.12559%",
    "volume": "$188.62K",
    "circulating_supply": "10.46K",
    "date": "26.11.2022",
    "assets": [
      "stETH",
      "WETH"
    ],
    "rank": 2
  },
  {
    "name": "Metaverse Index",
    "symbol": "mvi",
    "original_mcap": 3283007,
    "marketcap": "3.28M",
    "price_change": "6.15342%",
    "volume": "$3.98K",
    "circulating_supply": "166.97K",
    "date": "26.11.2022",
    "assets": [
      "ILV",
      "AXS",
      "SAND",
      "MANA",
      "ENJ",
      "WAXE",
      "RLY",
      "AUDIO",
      "YGG",
      "DG",
      "ERN",
      "NFTX",
      "Whale",
      "TVK",
      "RARI",
      "REVV"
    ],
    "rank": 3
  },
  {
    "name": "Bankless BED Index",
    "symbol": "bed",
    "original_mcap": 896084,
    "marketcap": "896.08K",
    "price_change": "3.25444%",
    "volume": "$1.05K",
    "circulating_supply": "20.69K",
    "date": "26.11.2022",
    "assets": [
      "WETH",
      "WBTC",
      "DPI"
    ],
    "rank": 4
  },
  {
    "name": "Data Economy Index",
    "symbol": "data",
    "original_mcap": 373642,
    "marketcap": "373.64K",
    "price_change": "4.18639%",
    "volume": "$2.37K",
    "circulating_supply": "22.61K",
    "date": "26.11.2022",
    "assets": [
      "LINK",
      "FIL",
      "GRAPH",
      "BAT",
      "LPT",
      "ENS",
      "OCEAN",
      "NMR"
    ],
    "rank": 5
  },
  {
    "name": "Bankless DeFi Innovation Index",
    "symbol": "gmi",
    "original_mcap": 341176,
    "marketcap": "341.18K",
    "price_change": "0.6631%",
    "volume": "$253.4",
    "circulating_supply": "26.63K",
    "date": "26.11.2022",
    "assets": [
      "CVX",
      "MPL",
      "TRIBE",
      "TOKE",
      "OLYMPUS",
      "RBN",
      "DYDX",
      "PERP",
      "FLX",
      "FXS",
      "ALCX",
      "DPX"
    ],
    "rank": 6
  },
  {
    "name": "JPG NFT Index",
    "symbol": "jpg",
    "original_mcap": 109583,
    "marketcap": "109.58K",
    "price_change": "2.69183%",
    "volume": "$11.65",
    "circulating_supply": "4.6K",
    "date": "26.11.2022",
    "assets": [
      "PUNK",
      "XMON",
      "WHALE",
      "SOCKS",
      "DOG",
      "ETH",
      "K21",
      "ASH",
      "uJenny"
    ],
    "rank": 7
  }
]