[
  {
    "id": "1669",
    "name": "TokensFarm",
    "address": null,
    "symbol": "-",
    "url": "https://tokensfarm.com",
    "description": "Multichain Farm-As-A-Service provider offering off-the-shelf farms for projects and a yield farming one-stop shop for crypto holders.",
    "chain": "Multi-Chain",
    "logo": "https://icons.llama.fi/tokensfarm.png",
    "audits": "2",
    "audit_note": null,
    "gecko_id": null,
    "cmcId": null,
    "category": "Farm",
    "chains": [
      "Binance",
      "Ethereum",
      "Polygon",
      "Fantom",
      "Avalanche"
    ],
    "oracles": [],
    "forkedFrom": [],
    "module": "tokensfarm/index.js",
    "twitter": "TokensFarm",
    "audit_links": [
      "https://www.certik.com/projects/tokensfarm"
    ],
    "listedAt": 1650460802,
    "slug": "tokensfarm",
    "tvl": 37048214.814924315,
    "chainTvls": {
      "Binance": 21106403.832489975,
      "Ethereum": 11675388.661792854,
      "Avalanche": 0,
      "Polygon": 4262287.028621622,
      "Fantom": 4135.292019858999
    },
    "change_1h": 0.07,
    "change_1d": 1.29,
    "change_7d": 1.22,
    "rank": 1
  },
  {
    "id": "833",
    "name": "ZoomSwap",
    "address": "iotex:0xf87aed04889a1dd0159d9C22B0D57b345Ab16dDD",
    "symbol": "ZM",
    "url": "https://zoomswap.io",
    "description": "Yield farming AMM in IoTeX!",
    "chain": "IoTeX",
    "logo": "https://icons.llama.fi/zoomswap.jpg",
    "audits": "2",
    "audit_note": null,
    "gecko_id": "zoomswap",
    "cmcId": null,
    "category": "Farm",
    "chains": [
      "IoTeX"
    ],
    "module": "zoomswap/index.js",
    "twitter": "zoomswap_io",
    "audit_links": [
      "https://rugdoc.io/project/zoomswap"
    ],
    "forkedFrom": [
      "Goose Finance"
    ],
    "listedAt": 1636756297,
    "slug": "zoomswap",
    "tvl": 2783693.9656857215,
    "chainTvls": {
      "pool2": 155524.4465211966,
      "IoTeX-staking": 75971.4038375123,
      "masterchef": 2783693.9656857215,
      "IoTeX-pool2": 155524.4465211966,
      "IoTeX": 2783693.9656857215,
      "IoTeX-masterchef": 2783693.9656857215,
      "staking": 75971.4038375123
    },
    "change_1h": 0.03,
    "change_1d": 0.17,
    "change_7d": -13.37,
    "staking": 75971.4038375123,
    "pool2": 155524.4465211966,
    "fdv": 542902,
    "mcap": 72641,
    "rank": 2
  },
  {
    "id": "205",
    "name": "Goose Finance",
    "address": "bsc:0xf952fc3ca7325cc27d15885d37117676d25bfda6",
    "symbol": "EGG",
    "url": "https://www.goosedefi.com/",
    "description": "2nd generation yield farming on binance smart chain",
    "chain": "Binance",
    "logo": "https://icons.llama.fi/goose-finance.jpg",
    "audits": "2",
    "audit_note": null,
    "gecko_id": "goose-finance",
    "cmcId": "8449",
    "category": "Farm",
    "chains": [
      "Binance"
    ],
    "module": "goose.js",
    "twitter": "Goosedefi",
    "audit_links": [
      "https://www.goosedefi.com/files/hackenAudit.pdf",
      "https://www.certik.org/projects/goose-finance"
    ],
    "forkedFrom": [
      "Uniswap"
    ],
    "slug": "goose-finance",
    "tvl": 1981763.55,
    "chainTvls": {
      "Binance": 1981763.55
    },
    "change_1h": 0.19,
    "change_1d": 0.64,
    "change_7d": 3.36,
    "fdv": 533894,
    "mcap": 519953,
    "rank": 3
  },
  {
    "id": "1781",
    "name": "SteakHut",
    "address": "avax:0xb279f8DD152B99Ec1D84A489D32c35bC0C7F5674",
    "symbol": "STEAK",
    "url": "https://www.steakhut.finance",
    "description": "Providing boosted Trader Joe liquidity pools and returning the profits to the Herd.",
    "chain": "Avalanche",
    "logo": "https://icons.llama.fi/steakhut.png",
    "audits": "2",
    "audit_note": null,
    "gecko_id": null,
    "cmcId": null,
    "category": "Farm",
    "chains": [
      "Avalanche"
    ],
    "oracles": [],
    "forkedFrom": [],
    "module": "steakHut/index.js",
    "twitter": "steakhut_fi",
    "audit_links": [
      "https://paladinsec.co/projects/steakhut-finance"
    ],
    "listedAt": 1653410101,
    "slug": "steakhut",
    "tvl": 1243717.851606767,
    "chainTvls": {
      "Avalanche": 1243717.851606767,
      "Avalanche-staking": 0,
      "staking": 0
    },
    "change_1h": -0.13,
    "change_1d": -0.08,
    "change_7d": 4.83,
    "staking": 0,
    "rank": 4
  },
  {
    "id": "599",
    "name": "Cub Finance",
    "address": "bsc:0x50d809c74e0b8e49e7b4c65bb3109abe3ff4c1c1",
    "symbol": "CUB",
    "url": "https://cubdefi.com",
    "description": "The goal of Cub Finance is to adopt and build DeFi-based smart contracts for the entire LeoFinance project. Through BEP20 LEO (bLEO), CUB and the adoption of existing use cases in the space, we're using the basic starting point of the Cub Finance yield platform to build a new generation of DeFi apps to expand and service our community of thousands of MAUs.",
    "chain": "Binance",
    "logo": "https://icons.llama.fi/cub-finance.svg",
    "audits": "2",
    "audit_note": null,
    "gecko_id": "cub-finance",
    "cmcId": "8858",
    "category": "Farm",
    "chains": [
      "Binance"
    ],
    "module": "cubfinance/index.js",
    "twitter": "FinanceLeo",
    "audit_links": [
      "https://www.certik.org/projects/cubfinance"
    ],
    "forkedFrom": [
      "Goose Finance",
      "Autofarm"
    ],
    "slug": "cub-finance",
    "tvl": 576773.6871169348,
    "chainTvls": {
      "Binance": 576773.6871169348
    },
    "change_1h": 0.57,
    "change_1d": 0.33,
    "change_7d": 2.83,
    "mcap": 398303,
    "rank": 5
  },
  {
    "id": "1375",
    "name": "Animal Farm",
    "address": "bsc:0x3A4C15F96B3b058ab3Fb5FAf1440Cc19E7AE07ce",
    "symbol": "PIGS",
    "url": "https://theanimal.farm",
    "description": "Masterchef Yield farm on BSC",
    "chain": "Binance",
    "logo": "https://icons.llama.fi/animal-farm.jpg",
    "audits": "0",
    "audit_note": null,
    "gecko_id": null,
    "cmcId": null,
    "category": "Farm",
    "chains": [
      "Binance"
    ],
    "oracles": [],
    "module": "animal-farm/index.js",
    "twitter": "DRIPcommunity",
    "language": "Solidity",
    "forkedFrom": [
      "SushiSwap"
    ],
    "listedAt": 1644437338,
    "slug": "animal-farm",
    "tvl": 511983.8391391122,
    "chainTvls": {
      "Binance-masterchef": 511983.8391391122,
      "pool2": 325795.64395669516,
      "masterchef": 511983.8391391122,
      "Binance-pool2": 325795.64395669516,
      "Binance": 511983.8391391122,
      "Binance-staking": 696028.553047666,
      "staking": 696028.553047666
    },
    "change_1h": -0.2,
    "change_1d": 1.88,
    "change_7d": 11.55,
    "staking": 696028.553047666,
    "pool2": 325795.64395669516,
    "rank": 6
  },
  {
    "id": "1281",
    "name": "veDAO",
    "address": "fantom:0x911da02c1232a3c3e1418b834a311921143b04d7",
    "symbol": "WeVE",
    "url": "https://www.vedao.io/",
    "description": "A masterchef",
    "chain": "Fantom",
    "logo": "https://icons.llama.fi/vedao.jpg",
    "audits": "3",
    "audit_note": null,
    "gecko_id": "vedao",
    "cmcId": "17459",
    "category": "Farm",
    "chains": [
      "Fantom"
    ],
    "module": "weve/index.js",
    "twitter": "_veDAO_",
    "forkedFrom": [
      "Uniswap"
    ],
    "listedAt": 1642528930,
    "slug": "vedao",
    "tvl": 285294.1774480972,
    "chainTvls": {
      "pool2": 14632.517931812628,
      "Fantom-staking": 0,
      "masterchef": 285294.17744809715,
      "Fantom-masterchef": 285294.17744809715,
      "Fantom-pool2": 14632.517931812628,
      "Fantom": 285294.1774480972,
      "staking": 0
    },
    "change_1h": 0.04,
    "change_1d": -0.06,
    "change_7d": -2.9,
    "staking": 0,
    "pool2": 14632.517931812628,
    "fdv": 740915,
    "mcap": 507029,
    "rank": 7
  },
  {
    "id": "590",
    "name": "Parrot Defi",
    "address": "arbitrum:0x78055dAA07035Aa5EBC3e5139C281Ce6312E1b22",
    "symbol": "PPEGG",
    "url": "https://parrotdefi.com",
    "description": "Yield farming and staking on the Arbitrum network.",
    "chain": "Multi-Chain",
    "logo": "https://icons.llama.fi/parrot-defi.png",
    "audits": "0",
    "audit_note": null,
    "gecko_id": null,
    "cmcId": null,
    "category": "Farm",
    "chains": [
      "IoTeX",
      "Arbitrum",
      "Polygon",
      "Harmony"
    ],
    "module": "parrotegg/index.js",
    "twitter": "Parrotdefi1",
    "forkedFrom": [
      "Goose Finance"
    ],
    "slug": "parrot-defi",
    "tvl": 135719.85183401656,
    "chainTvls": {
      "IoTeX": 124991.14754881861,
      "Polygon": 3891.078837077187,
      "Arbitrum": 6027.394515969889,
      "Harmony": 810.2309321508635
    },
    "change_1h": 0.28,
    "change_1d": 0.46,
    "change_7d": 0.31,
    "rank": 8
  },
  {
    "id": "675",
    "name": "Dark Matter",
    "address": "fantom:0x90e892fed501ae00596448aecf998c88816e5c0f",
    "symbol": "DMD",
    "url": "https://www.dmu.zone",
    "description": "Dark Matter employs its native token, DMD, in all aspects of its ecosystem, including governance. At launch, you are able to stake, pool, and earn DMD. Additional use cases are in development, featuring NFTs and more.",
    "chain": "Fantom",
    "logo": "https://icons.llama.fi/dark-matter.jpg",
    "audits": "0",
    "audit_note": null,
    "gecko_id": "dark-matter-defi",
    "cmcId": "12675",
    "category": "Farm",
    "chains": [
      "Fantom"
    ],
    "module": "darkmatter/index.js",
    "twitter": "darkmatterdefi",
    "forkedFrom": [
      "Goose Finance"
    ],
    "listedAt": 1634342862,
    "slug": "dark-matter",
    "tvl": 77569.24453599642,
    "chainTvls": {
      "pool2": 12099.185128440848,
      "Fantom-staking": 22521.505252648243,
      "Fantom-pool2": 12099.185128440848,
      "staking": 22521.505252648243,
      "Fantom": 77569.24453599642
    },
    "change_1h": 0.13,
    "change_1d": 0.17,
    "change_7d": 0.75,
    "staking": 22521.505252648243,
    "pool2": 12099.185128440848,
    "fdv": 354190,
    "mcap": 0,
    "rank": 9
  },
  {
    "id": "1810",
    "name": "Zinax DAO",
    "address": "bsc:0xFf3Aa0D4874C3BD5AdcBB94254005ff19f798AcB",
    "symbol": "ZINAX",
    "url": "https://zinax.org",
    "description": "ZinaX DAO is a fixed deposit bank, built on the blockchain. ZinaX provides high yield savings and mining DeFi pools for crypto enthusiasts.",
    "chain": "Binance",
    "logo": "https://icons.llama.fi/zinax-dao.png",
    "audits": "0",
    "audit_note": null,
    "gecko_id": null,
    "cmcId": null,
    "category": "Farm",
    "chains": [
      "Binance"
    ],
    "oracles": [],
    "forkedFrom": [],
    "module": "zinaxdao/index.js",
    "twitter": "zinaxtoken",
    "listedAt": 1654622081,
    "slug": "zinax-dao",
    "tvl": 55360.10086190986,
    "chainTvls": {
      "Binance-masterchef": 55360.10086190986,
      "pool2": 6353.739816912905,
      "masterchef": 55360.10086190986,
      "Binance-pool2": 6353.739816912905,
      "Binance": 55360.10086190986,
      "Binance-staking": 26863.37752822333,
      "staking": 26863.37752822333
    },
    "change_1h": 0.05,
    "change_1d": -7.92,
    "change_7d": -2.43,
    "staking": 26863.37752822333,
    "pool2": 6353.739816912905,
    "rank": 10
  },
  {
    "id": "1436",
    "name": "SpectreFi",
    "address": "fantom:0x2834d4F4cC40bd7D78c07E2D848358364222C272",
    "symbol": "SPECT",
    "url": "https://spectrefi.com",
    "description": "Revolutionary DeFi Yield Farm on Fantom chain with referral system to give you that extra boost. Astral Farm also has auto-burn and auto-liquidity to ensure sustainably native price.",
    "chain": "Fantom",
    "logo": "https://icons.llama.fi/spectrefi.png",
    "audits": "0",
    "audit_note": null,
    "gecko_id": null,
    "cmcId": null,
    "category": "Farm",
    "chains": [
      "Fantom"
    ],
    "oracles": [],
    "forkedFrom": [
      "Goose Finance"
    ],
    "module": "spectrefi/index.js",
    "twitter": "SpectreDefi",
    "listedAt": 1645299360,
    "slug": "spectrefi",
    "tvl": 36334.6678178363,
    "chainTvls": {
      "pool2": 232.24318396975713,
      "Fantom-staking": 0,
      "Fantom-pool2": 232.24318396975713,
      "staking": 0,
      "Fantom": 36334.6678178363
    },
    "change_1h": -0.09,
    "change_1d": 0.05,
    "change_7d": 0.16,
    "staking": 0,
    "pool2": 232.24318396975713,
    "rank": 11
  },
  {
    "id": "1163",
    "name": "Trick or Treat Farm",
    "address": "fantom:0xA5aFce54270D9afA6a80464bBD383BE506888e6A",
    "symbol": "TRICK",
    "url": "https://trickortreat.farm/",
    "description": "Trick or Treat Farm aims to provide a safe and fortuitous place for newcomers and veterans alike to increase the yields on cryptocurrency tokens deposited in the farm.",
    "chain": "Fantom",
    "logo": "https://icons.llama.fi/trick-or-treat-farm.png",
    "audits": "2",
    "audit_note": null,
    "gecko_id": "trick",
    "cmcId": null,
    "category": "Farm",
    "chains": [
      "Fantom"
    ],
    "module": "trickortreat/index.js",
    "twitter": "tricktreatfarm",
    "audit_links": [
      "https://github.com/solidproof/smart-contract-audits/blob/main/SmartContract_Audit_Solidproof_TrickOrTreat.pdf"
    ],
    "forkedFrom": [
      "Goose Finance"
    ],
    "listedAt": 1640909035,
    "slug": "trick-or-treat-farm",
    "tvl": 34462.93643085271,
    "chainTvls": {
      "pool2": 106.02663180933503,
      "Fantom-staking": 0,
      "Fantom-pool2": 106.02663180933503,
      "staking": 0,
      "Fantom": 34462.93643085271
    },
    "change_1h": -0.07,
    "change_1d": 0.44,
    "change_7d": -1.24,
    "staking": 0,
    "pool2": 106.02663180933503,
    "fdv": 228.58,
    "mcap": 0,
    "rank": 12
  },
  {
    "id": "1149",
    "name": "Koala Defi",
    "address": "bsc:0xb2ebaa0ad65e9c888008bf10646016f7fcdd73c3",
    "symbol": "NALIS",
    "url": "https://koaladefi.finance/",
    "description": "High security crosschain Yieldfarming DAPP and crypto platform running on the Binance Smart Chain (BSC) and Polygon chain using the ApeSwap Exchange.",
    "chain": "Multi-Chain",
    "logo": "https://icons.llama.fi/koala-defi.png",
    "audits": "2",
    "audit_note": null,
    "gecko_id": null,
    "cmcId": null,
    "category": "Farm",
    "chains": [
      "Binance",
      "Polygon"
    ],
    "module": "koala-defi/index.js",
    "twitter": "KoalaDefi",
    "audit_links": [
      "https://doc.koaladefi.finance/security/audits/audit-binance-smart-chain-bsc",
      "https://doc.koaladefi.finance/security/audits/audit-polygon"
    ],
    "forkedFrom": [
      "Goose Finance"
    ],
    "listedAt": 1640808769,
    "slug": "koala-defi",
    "tvl": 13022.182025181248,
    "chainTvls": {
      "pool2": 2802.918222875168,
      "Polygon-pool2": 176.71107568882235,
      "Binance-pool2": 2626.2071471863455,
      "Binance": 11975.190394847901,
      "Binance-staking": 1344.9128885883297,
      "Polygon": 1046.9916303333473,
      "Polygon-staking": 139.529551161,
      "staking": 1484.4424397493297
    },
    "change_1h": 0.14,
    "change_1d": 0.95,
    "change_7d": 3.16,
    "staking": 1484.4424397493297,
    "pool2": 2802.918222875168,
    "rank": 13
  },
  {
    "id": "1324",
    "name": "FuryLabs Finance",
    "address": "fantom:0xB1822A7ee73DD7de6Eda328A0681f8E1779CC4B6",
    "symbol": "FURY",
    "url": "https://furylabsfinance.com",
    "description": "Masterchef yield farming on Fantom",
    "chain": "Fantom",
    "logo": "https://icons.llama.fi/furylabs-finance.jpg",
    "audits": "2",
    "audit_note": null,
    "gecko_id": null,
    "cmcId": null,
    "category": "Farm",
    "chains": [
      "Fantom"
    ],
    "module": "furylabsfinance/index.js",
    "twitter": "FuryLabs_",
    "audit_links": [
      "https://fury-labs.gitbook.io/faq/security"
    ],
    "forkedFrom": [
      "Uniswap"
    ],
    "listedAt": 1643397175,
    "slug": "furylabs-finance",
    "tvl": 11634.66564675926,
    "chainTvls": {
      "pool2": 130.56371386273352,
      "Fantom-staking": 96.00889498199999,
      "masterchef": 11634.665646759262,
      "Fantom-masterchef": 11634.665646759262,
      "Fantom-pool2": 130.56371386273352,
      "Fantom": 11634.66564675926,
      "staking": 96.00889498199999
    },
    "change_1h": 0.09,
    "change_1d": 0.11,
    "change_7d": 3.03,
    "staking": 96.00889498199999,
    "pool2": 130.56371386273352,
    "rank": 14
  },
  {
    "id": "523",
    "name": "CryptoYieldFocus",
    "address": "avax:0x411491859864797792308723Fc417f11BbA18D1b",
    "symbol": "CYF",
    "url": "https://www.cryptoyieldfocus.com",
    "description": "Newly-launched yield farm and AMM based on Avalanche. Our goal is to create a strong and trustworthy foundation for which to be built upon by other businesses and clients alike. Brand new functions and utilities will be added upon our CYF token to sustain an enjoyable and immersive environment for our users",
    "chain": "Avalanche",
    "logo": "https://icons.llama.fi/cryptoyieldfocus.jpg",
    "audits": "0",
    "audit_note": null,
    "gecko_id": null,
    "cmcId": null,
    "category": "Farm",
    "chains": [
      "Avalanche"
    ],
    "module": "cryptoyieldfocus/index.js",
    "twitter": "CryptYieldFocus",
    "forkedFrom": [
      "Goose Finance"
    ],
    "slug": "cryptoyieldfocus",
    "tvl": 4852.216491504872,
    "chainTvls": {
      "Avalanche": 4852.216491504872,
      "Avalanche-staking": 0,
      "pool2": 6.201492185818923,
      "Avalanche-pool2": 6.201492185818923,
      "staking": 0
    },
    "change_1h": 0.02,
    "change_1d": 0.68,
    "change_7d": 6.37,
    "staking": 0,
    "pool2": 6.201492185818923,
    "rank": 15
  },
  {
    "id": "1308",
    "name": "Frog Nation Farm",
    "address": "fantom:0xfa5c941bc491ee6dc1e933f38d01d8b5d5637205",
    "symbol": "FROG",
    "url": "https://www.frognation.farm/",
    "description": "Frog Nation Farm is a yield farm on the Fantom Opera Network.",
    "chain": "Fantom",
    "logo": "https://icons.llama.fi/frog-nation-farm.png",
    "audits": "0",
    "audit_note": null,
    "gecko_id": "frog-nation-farm",
    "cmcId": null,
    "category": "Farm",
    "chains": [
      "Fantom"
    ],
    "module": "frog-nation-farm/index.js",
    "twitter": "frognation_farm",
    "forkedFrom": [
      "Goose Finance"
    ],
    "listedAt": 1642809400,
    "slug": "frog-nation-farm",
    "tvl": 3710.9494165683373,
    "chainTvls": {
      "pool2": 23.404206697161644,
      "Fantom-staking": 0,
      "masterchef": 3710.9494165683373,
      "Fantom-masterchef": 3710.9494165683373,
      "Fantom-pool2": 23.404206697161644,
      "Fantom": 3710.9494165683373,
      "staking": 0
    },
    "change_1h": -0.01,
    "change_1d": -0.05,
    "change_7d": 0.57,
    "staking": 0,
    "pool2": 23.404206697161644,
    "mcap": 0,
    "rank": 16
  },
  {
    "id": "1435",
    "name": "Cemetery Finance",
    "address": "fantom:0x8bD04EE83a6076d1216237C8B91f7EeE3AccaB35",
    "symbol": "HAUNT",
    "url": "https://www.cemetery.finance",
    "description": "Cemetery Finance is a farm with the simple purpose of generating passive income for users of the fantom ecosystem with sustainable and persistent gains, bringing balanced issuances and greater incentives to holders of the native HAUNT token.",
    "chain": "Fantom",
    "logo": "https://icons.llama.fi/cementary-finance.png",
    "audits": "0",
    "audit_note": null,
    "gecko_id": null,
    "cmcId": null,
    "category": "Farm",
    "chains": [
      "Fantom"
    ],
    "oracles": [],
    "forkedFrom": [
      "Goose Finance"
    ],
    "module": "cemetery/index.js",
    "twitter": "cemeteryfinance",
    "listedAt": 1645299174,
    "slug": "cemetery-finance",
    "tvl": 3689.6244773850613,
    "chainTvls": {
      "pool2": 25.993776543100793,
      "Fantom-staking": 0,
      "Fantom-pool2": 25.993776543100793,
      "staking": 0,
      "Fantom": 3689.6244773850613
    },
    "change_1h": 0.06,
    "change_1d": 0.25,
    "change_7d": 1.87,
    "staking": 0,
    "pool2": 25.993776543100793,
    "rank": 17
  },
  {
    "id": "1607",
    "name": "Milko Farm",
    "address": "milkomeda:0x3c786134228b363fb2984619D7560AB56363B2bD",
    "symbol": "MLK",
    "url": "https://www.milko.farm",
    "description": "YieldFarming on Milkomeda Network",
    "chain": "Milkomeda",
    "logo": "https://icons.llama.fi/milko-farm.png",
    "audits": "0",
    "audit_note": null,
    "gecko_id": null,
    "cmcId": null,
    "category": "Farm",
    "chains": [
      "Milkomeda"
    ],
    "oracles": [],
    "forkedFrom": [
      "Goose Finance"
    ],
    "module": "milko-farm.js",
    "twitter": "milko_farm",
    "listedAt": 1649072088,
    "slug": "milko-farm",
    "tvl": 3673.1000024096056,
    "chainTvls": {
      "pool2": 56.53782649221603,
      "Milkomeda": 3673.1000024096056,
      "masterchef": 3673.1000024096056,
      "Milkomeda-masterchef": 3673.1000024096056,
      "Milkomeda-pool2": 56.53782649221603,
      "Milkomeda-staking": 135.86674711199998,
      "staking": 135.86674711199998
    },
    "change_1h": 0.26,
    "change_1d": 2.54,
    "change_7d": 8.22,
    "staking": 135.86674711199998,
    "pool2": 56.53782649221603,
    "rank": 18
  },
  {
    "id": "1328",
    "name": "Astral Farm",
    "address": "fantom:0xd95322C0D069B51a41ed2D94A39617C2ACbcE636",
    "symbol": "ASTRAL",
    "url": "https://astral-farm.com",
    "description": "Revolutionary DeFi Yield Farm on Fantom chain with referral system to give you that extra boost. Astral Farm also has auto-burn and auto-liquidity to ensure sustainably native price.",
    "chain": "Fantom",
    "logo": "https://icons.llama.fi/astral-farm.png",
    "audits": "0",
    "audit_note": null,
    "gecko_id": "astral-farm",
    "cmcId": null,
    "category": "Farm",
    "chains": [
      "Fantom"
    ],
    "module": "astralfarm/index.js",
    "twitter": "Astral_FTM",
    "oracles": [],
    "forkedFrom": [
      "Goose Finance"
    ],
    "listedAt": 1643481742,
    "slug": "astral-farm",
    "tvl": 3378.0540007067475,
    "chainTvls": {
      "pool2": 5.604758102457634,
      "Fantom-staking": 120.11790852367697,
      "Fantom-pool2": 5.604758102457634,
      "staking": 120.11790852367697,
      "Fantom": 3378.0540007067475
    },
    "change_1h": 0.03,
    "change_1d": 0.12,
    "change_7d": 1.81,
    "staking": 120.11790852367697,
    "pool2": 5.604758102457634,
    "fdv": 1436.37,
    "mcap": 0,
    "rank": 19
  },
  {
    "id": "1533",
    "name": "LIFE",
    "address": "fantom:0x8877E4B70C50CF275C2B77d6a0F69a312F5eE236",
    "symbol": "LIFE",
    "url": "https://lif3.exchange/",
    "description": "LIFE is a reward and governance token integrating DeFi yield farming on the Fantom network. Earn yield from your ERC-20 tokens and LP tokens by staking and earning LIFE rewards.",
    "chain": "Fantom",
    "logo": "https://icons.llama.fi/blindex.jpg",
    "audits": "0",
    "audit_note": null,
    "gecko_id": null,
    "cmcId": null,
    "category": "Farm",
    "chains": [
      "Fantom"
    ],
    "oracles": [],
    "forkedFrom": [
      "Goose Finance"
    ],
    "module": "life/index.js",
    "twitter": "DefiFatfire",
    "listedAt": 1646953849,
    "slug": "life",
    "tvl": 2337.3914986057525,
    "chainTvls": {
      "pool2": 4.08097480006157,
      "Fantom-staking": 15.655353163840886,
      "masterchef": 2337.3914986057525,
      "Fantom-masterchef": 2337.3914986057525,
      "Fantom-pool2": 4.08097480006157,
      "Fantom": 2337.3914986057525,
      "staking": 15.655353163840886
    },
    "change_1h": 0.28,
    "change_1d": 0.7,
    "change_7d": 7.11,
    "staking": 15.655353163840886,
    "pool2": 4.08097480006157,
    "rank": 20
  },
  {
    "id": "1437",
    "name": "Nightmare Finance",
    "address": "fantom:0x465d67204A8F7c02cd35288Cc7712526359FB0a9",
    "symbol": "FEAR",
    "url": "https://www.nightmarefinance.com",
    "description": "Powered by Fantom (FTM) with its high-speed consensus mechanism, Earn FEAR through yield farming or via our Incentives Pools and Vault Staking",
    "chain": "Fantom",
    "logo": "https://icons.llama.fi/nightmare-finance.png",
    "audits": "0",
    "audit_note": null,
    "gecko_id": null,
    "cmcId": null,
    "category": "Farm",
    "chains": [
      "Fantom"
    ],
    "oracles": [],
    "forkedFrom": [
      "Goose Finance"
    ],
    "module": "nightmare/index.js",
    "twitter": "Nightmare_fi",
    "listedAt": 1645299462,
    "slug": "nightmare-finance",
    "tvl": 2277.1921999644883,
    "chainTvls": {
      "pool2": 7.470670258600622,
      "Fantom-staking": 0,
      "Fantom-pool2": 7.470670258600622,
      "staking": 0,
      "Fantom": 2277.1921999644883
    },
    "change_1h": 0.29,
    "change_1d": 2.1,
    "change_7d": 10.1,
    "staking": 0,
    "pool2": 7.470670258600622,
    "rank": 21
  },
  {
    "id": "1479",
    "name": "Phantom Finance",
    "address": "fantom:0x6230a87901C2ca6b23247a9afC1f63A8ecb95B05",
    "symbol": "PHANTOM",
    "url": "https://www.phantom.farm",
    "description": "Yield Farm on Fantom",
    "chain": "Fantom",
    "logo": "https://icons.llama.fi/gton-capital.png",
    "audits": "0",
    "audit_note": null,
    "gecko_id": null,
    "cmcId": null,
    "category": "Farm",
    "chains": [
      "Fantom"
    ],
    "oracles": [],
    "forkedFrom": [
      "Goose Finance"
    ],
    "module": "phantom-finance/index.js",
    "twitter": "Phantom_fi",
    "listedAt": 1645901674,
    "slug": "phantom-finance",
    "tvl": 1809.9628020712273,
    "chainTvls": {
      "pool2": 82.78094075074699,
      "Fantom-staking": 0,
      "Fantom-pool2": 82.78094075074699,
      "staking": 0,
      "Fantom": 1809.9628020712273
    },
    "change_1h": 0.06,
    "change_1d": 0.01,
    "change_7d": 1.92,
    "staking": 0,
    "pool2": 82.78094075074699,
    "rank": 22
  },
  {
    "id": "1623",
    "name": "TroyDefi",
    "address": "bsc:0x576BB65B52425d59AC4c702376F88c527f5C7773",
    "symbol": "TROY",
    "url": "https://www.troydefi.com",
    "description": "TroyDefi is a Binance Smart Chain yield farming project with high yields and a limited supply of 500,000 TROY tokens. Binance Smart Chain (BSC) solves many issues that exist on the Ethereum network.",
    "chain": "Binance",
    "logo": "https://icons.llama.fi/troydefi.png",
    "audits": "2",
    "audit_note": null,
    "gecko_id": null,
    "cmcId": null,
    "category": "Farm",
    "chains": [
      "Binance"
    ],
    "oracles": [],
    "forkedFrom": [],
    "module": "troydefi/index.js",
    "twitter": "TroyDefi",
    "audit_links": [
      "https://rugdoc.io/project/troy-defi"
    ],
    "listedAt": 1649319546,
    "slug": "troydefi",
    "tvl": 1289.6143787768178,
    "chainTvls": {
      "Binance-masterchef": 1289.6143787768178,
      "pool2": 148.54895253648493,
      "masterchef": 1289.6143787768178,
      "Binance-pool2": 148.54895253648493,
      "Binance": 1289.6143787768178,
      "Binance-staking": 86.14068197916005,
      "staking": 86.14068197916005
    },
    "change_1h": 0.18,
    "change_1d": 0.51,
    "change_7d": 1.66,
    "staking": 86.14068197916005,
    "pool2": 148.54895253648493,
    "rank": 23
  },
  {
    "id": "1606",
    "name": "Mockingbird",
    "address": "fantom:0x0A737c40E42b164B30c0d3E5A19152CB89aA3EB9",
    "symbol": "MOCKINGBIRD",
    "url": "https://mockingbird.philetairus-socius.com",
    "description": "Yield farm on Fantom",
    "chain": "Fantom",
    "logo": "https://icons.llama.fi/mockingbird.png",
    "audits": "0",
    "audit_note": null,
    "gecko_id": null,
    "cmcId": null,
    "category": "Farm",
    "chains": [
      "Fantom"
    ],
    "oracles": [],
    "forkedFrom": [
      "Goose Finance"
    ],
    "module": "mockingbird/index.js",
    "twitter": "philetairus",
    "listedAt": 1649014284,
    "slug": "mockingbird",
    "tvl": 1132.5281347184648,
    "chainTvls": {
      "pool2": 0.896337611589042,
      "Fantom-staking": 0,
      "Fantom-pool2": 0.896337611589042,
      "staking": 0,
      "Fantom": 1132.5281347184648
    },
    "change_1h": 0.05,
    "change_1d": -0.12,
    "change_7d": 0.98,
    "staking": 0,
    "pool2": 0.896337611589042,
    "rank": 24
  },
  {
    "id": "843",
    "name": "Unirex Finance",
    "address": "fantom:0x350a911687EB9710f1D36792F26D419577B127A8",
    "symbol": "UNIREX",
    "url": "https://www.unirex.finance",
    "description": "Unirex Finance is a decentralized farm yield project running on Fantom Chain, Polygon (soon), and BSC (soon).",
    "chain": "Fantom",
    "logo": "https://icons.llama.fi/unirex-finance.png",
    "audits": "0",
    "audit_note": null,
    "gecko_id": null,
    "cmcId": null,
    "category": "Farm",
    "chains": [
      "Fantom"
    ],
    "module": "unirexfinance/index.js",
    "twitter": "UnirexFinance",
    "forkedFrom": [
      "Goose Finance"
    ],
    "listedAt": 1637026454,
    "slug": "unirex-finance",
    "tvl": 1035.3678482303867,
    "chainTvls": {
      "pool2": 9.662046485026632,
      "Fantom-staking": 0,
      "Fantom-pool2": 9.662046485026632,
      "staking": 0,
      "Fantom": 1035.3678482303867
    },
    "change_1h": -0.13,
    "change_1d": -0.21,
    "change_7d": 0.73,
    "staking": 0,
    "pool2": 9.662046485026632,
    "rank": 25
  },
  {
    "id": "710",
    "name": "Squid-Defi",
    "address": "fantom:0xd86Be84feC60Fedf263059BB1581e00d2168e19D",
    "symbol": "SQUID",
    "url": "https://squid-defi.com",
    "description": "#1 Stable DeFi Token on the Fantom Blockchain",
    "chain": "Fantom",
    "logo": "https://icons.llama.fi/squid-defi.png",
    "audits": "0",
    "audit_note": null,
    "gecko_id": null,
    "cmcId": null,
    "category": "Farm",
    "chains": [
      "Fantom"
    ],
    "module": "squid-defi/index.js",
    "twitter": "SquidDeFi",
    "forkedFrom": [
      "Goose Finance"
    ],
    "listedAt": 1635249537,
    "slug": "squid-defi",
    "tvl": 1007.102917469799,
    "chainTvls": {
      "pool2": 34.70835869869489,
      "Fantom-staking": 0,
      "Fantom-pool2": 34.70835869869489,
      "staking": 0,
      "Fantom": 1007.102917469799
    },
    "change_1h": -0.06,
    "change_1d": -0.36,
    "change_7d": 5.55,
    "staking": 0,
    "pool2": 34.70835869869489,
    "rank": 26
  }
]